{
  "$schema": "https://developer.microsoft.com/json-schemas/fabric/item/report/definition/visualContainer/2.4.0/schema.json",
  "name": "9b6a3bfeab0184bf7af5",
  "position": {
    "x": 569.65775569750008,
    "y": 0,
    "z": 1000,
    "height": 40,
    "width": 40,
    "tabOrder": 0
  },
  "visual": {
    "visualType": "image",
    "objects": {
      "general": [
        {
          "properties": {
            "imageUrl": {
              "expr": {
                "ResourcePackageItem": {
                  "PackageName": "RegisteredResources",
                  "PackageType": 1,
                  "ItemName": "icons8-filtro-969493399617397431.png"
                }
              }
            }
          }
        }
      ]
    },
    "visualContainerObjects": {
      "lockAspect": [
        {
          "properties": {
            "show": {
              "expr": {
                "Literal": {
                  "Value": "false"
                }
              }
            }
          }
        }
      ],
      "title": [
        {
          "properties": {
            "text": {
              "expr": {
                "Literal": {
                  "Value": "'exibir-filtro'"
                }
              }
            }
          }
        }
      ],
      "visualLink": [
        {
          "properties": {
            "show": {
              "expr": {
                "Literal": {
                  "Value": "true"
                }
              }
            },
            "type": {
              "expr": {
                "Literal": {
                  "Value": "'Bookmark'"
                }
              }
            },
            "bookmark": {
              "expr": {
                "Literal": {
                  "Value": "'6a3d6e99f182e4e6c33c'"
                }
              }
            }
          }
        }
      ]
    },
    "drillFilterOtherVisuals": true
  },
  "parentGroupName": "c8f41c81e30542fa8c12",
  "howCreated": "InsertVisualButton"
}